{
  "id": 19064,
  "collectionId": 3002,
  "series": 103401,
  "taskType": "LQ",
  "enabled": true,
  "luaPath": "Actor/Quest/LQ19064",
  "recommendLevel": 0,
  "repeatable": false,
  "chapterId": 103401,
  "subQuests": [
    {
      "subId": 1906401,
      "mainId": 19064,
      "order": 1,
      "subQuestGroup": 0,
      "isMpBlock": false,
      "acceptCondComb": "LOGIC_AND",
      "acceptCond": [
        {
          "type": "QUEST_COND_STATE_EQUAL",
          "param": [
            1906104,
            3
          ],
          "count": 0
        },
        {
          "type": "QUEST_COND_MAIN_COOP_ENTER_SAVE_POINT",
          "param": [
            103401,
            190610102
          ],
          "count": 0
        }
      ],
      "finishCond": [
        {
          "type": "QUEST_CONTENT_LUA_NOTIFY",
          "paramStr": "1330044451",
          "count": 1
        }
      ],
      "guide": {
        "type": "QUEST_GUIDE_LOCATION",
        "autoGuide": "QUEST_GUIDE_AUTO_ENABLE",
        "param": [
          "Q19064TrainingPlayer"
        ],
        "guideScene": 3,
        "guideStyle": "QUEST_GUIDE_STYLE_POINT",
        "guideLayer": "QUEST_GUIDE_LAYER_SCENE"
      },
      "showGuide": false,
      "finishParent": false,
      "failParent": false,
      "isRewind": true,
      "beginExec": [
        {
          "type": "QUEST_EXEC_REFRESH_GROUP_SUITE",
          "param": [
            "3",
            "133004445,3"
          ]
        }
      ],
      "exclusiveNpcList": [
        1027,
        1605
      ],
      "exclusivePriority": 1100,
      "coopPointIdList": [
        10340105
      ],
      "refreshNonCoopOnly": false
    },
    {
      "subId": 1906402,
      "mainId": 19064,
      "order": 2,
      "subQuestGroup": 0,
      "isMpBlock": true,
      "acceptCondComb": "LOGIC_AND",
      "acceptCond": [
        {
          "type": "QUEST_COND_STATE_EQUAL",
          "param": [
            1906401,
            3
          ],
          "count": 0
        }
      ],
      "finishCond": [
        {
          "type": "QUEST_CONTENT_MAIN_COOP_ENTER_ANY_SAVE_POINT",
          "param": [
            103401
          ],
          "count": 0
        }
      ],
      "failCondComb": "LOGIC_OR",
      "failCond": [
        {
          "type": "QUEST_CONTENT_ANY_MANUAL_TRANSPORT",
          "count": 0
        },
        {
          "type": "QUEST_CONTENT_ENTER_MY_WORLD",
          "param": [
            3
          ],
          "count": 0
        },
        {
          "type": "QUEST_CONTENT_TEAM_DEAD",
          "count": 0
        },
        {
          "type": "QUEST_CONTENT_NOT_FINISH_PLOT",
          "param": [
            1906403
          ],
          "count": 0
        }
      ],
      "guide": {
        "type": "QUEST_GUIDE_NPC",
        "autoGuide": "QUEST_GUIDE_AUTO_ENABLE",
        "param": [
          "1027"
        ],
        "guideScene": 3,
        "guideStyle": "QUEST_GUIDE_STYLE_TARGET",
        "guideLayer": "QUEST_GUIDE_LAYER_SCENE"
      },
      "showGuide": false,
      "finishParent": false,
      "failParent": false,
      "isRewind": false,
      "failExec": [
        {
          "type": "QUEST_EXEC_REMOVE_TRIAL_AVATAR",
          "param": [
            "500"
          ]
        },
        {
          "type": "QUEST_EXEC_ROLLBACK_QUEST",
          "param": [
            "1906401"
          ]
        }
      ],
      "exclusiveNpcList": [
        1027,
        1605
      ],
      "exclusivePriority": 1100,
      "coopPointIdList": [
        10340105
      ],
      "refreshNonCoopOnly": false
    },
    {
      "subId": 1906403,
      "mainId": 19064,
      "order": 3,
      "subQuestGroup": 0,
      "isMpBlock": true,
      "acceptCondComb": "LOGIC_AND",
      "acceptCond": [
        {
          "type": "QUEST_COND_STATE_EQUAL",
          "param": [
            1906402,
            3
          ],
          "count": 0
        }
      ],
      "finishCond": [
        {
          "type": "QUEST_CONTENT_LUA_NOTIFY",
          "paramStr": "1330044452",
          "count": 1
        }
      ],
      "failCondComb": "LOGIC_OR",
      "failCond": [
        {
          "type": "QUEST_CONTENT_NOT_FINISH_PLOT",
          "param": [
            1906403
          ],
          "count": 0
        },
        {
          "type": "QUEST_CONTENT_ANY_MANUAL_TRANSPORT",
          "count": 0
        },
        {
          "type": "QUEST_CONTENT_TEAM_DEAD",
          "count": 0
        },
        {
          "type": "QUEST_CONTENT_ENTER_MY_WORLD",
          "param": [
            3
          ],
          "count": 0
        }
      ],
      "guide": {
        "type": "QUEST_GUIDE_LOCATION",
        "autoGuide": "QUEST_GUIDE_AUTO_ENABLE",
        "param": [
          "Q19064TrainingArea",
          "20"
        ],
        "guideScene": 3,
        "guideStyle": "QUEST_GUIDE_STYLE_TARGET",
        "guideLayer": "QUEST_GUIDE_LAYER_SCENE"
      },
      "showGuide": true,
      "finishParent": false,
      "failParent": false,
      "isRewind": false,
      "failExec": [
        {
          "type": "QUEST_EXEC_UNLOCK_AVATAR_TEAM"
        },
        {
          "type": "QUEST_EXEC_REMOVE_TRIAL_AVATAR",
          "param": [
            "500"
          ]
        },
        {
          "type": "QUEST_EXEC_ROLLBACK_QUEST",
          "param": [
            "1906401"
          ]
        }
      ],
      "beginExec": [
        {
          "type": "QUEST_EXEC_GRANT_TRIAL_AVATAR_AND_LOCK_TEAM",
          "param": [
            "500"
          ]
        }
      ],
      "exclusiveNpcList": [
        1027,
        1605
      ],
      "exclusivePriority": 1100,
      "trialAvatarList": [
        500
      ],
      "coopPointIdList": [
        10340105
      ],
      "refreshNonCoopOnly": false
    },
    {
      "subId": 1906404,
      "mainId": 19064,
      "order": 4,
      "subQuestGroup": 0,
      "isMpBlock": false,
      "acceptCondComb": "LOGIC_AND",
      "acceptCond": [
        {
          "type": "QUEST_COND_STATE_EQUAL",
          "param": [
            1906403,
            3
          ],
          "count": 0
        }
      ],
      "finishCond": [
        {
          "type": "QUEST_CONTENT_MAIN_COOP_ENTER_ANY_SAVE_POINT",
          "param": [
            103401
          ],
          "count": 0
        }
      ],
      "guide": {
        "type": "QUEST_GUIDE_NPC",
        "autoGuide": "QUEST_GUIDE_AUTO_ENABLE",
        "param": [
          "1027"
        ],
        "guideScene": 3,
        "guideStyle": "QUEST_GUIDE_STYLE_TARGET",
        "guideLayer": "QUEST_GUIDE_LAYER_SCENE"
      },
      "showGuide": false,
      "finishParent": true,
      "failParent": false,
      "isRewind": true,
      "beginExec": [
        {
          "type": "QUEST_EXEC_UNLOCK_AVATAR_TEAM"
        },
        {
          "type": "QUEST_EXEC_REFRESH_GROUP_SUITE",
          "param": [
            "3",
            "133004445,1"
          ]
        },
        {
          "type": "QUEST_EXEC_REMOVE_TRIAL_AVATAR",
          "param": [
            "500"
          ]
        }
      ],
      "exclusiveNpcList": [
        1027,
        1605
      ],
      "exclusivePriority": 1100,
      "coopPointIdList": [
        10340105
      ],
      "refreshNonCoopOnly": false
    },
    {
      "subId": 1906405,
      "mainId": 19064,
      "order": 5,
      "subQuestGroup": 0,
      "isMpBlock": false,
      "showType": "QUEST_HIDDEN",
      "acceptCondComb": "LOGIC_AND",
      "acceptCond": [
        {
          "type": "QUEST_COND_STATE_EQUAL",
          "param": [
            1906401,
            3
          ],
          "count": 0
        }
      ],
      "finishCond": [
        {
          "type": "QUEST_CONTENT_FINISH_PLOT",
          "param": [
            1906405
          ],
          "count": 0
        }
      ],
      "failCond": [
        {
          "type": "QUEST_CONTENT_MAIN_COOP_ENTER_ANY_SAVE_POINT",
          "param": [
            103401
          ],
          "count": 0
        }
      ],
      "guide": {
        "guideScene": 3
      },
      "showGuide": true,
      "finishParent": false,
      "failParent": false,
      "isRewind": false,
      "finishExec": [
        {
          "type": "QUEST_EXEC_REFRESH_GROUP_SUITE",
          "param": [
            "3",
            "133004445,2"
          ]
        }
      ],
      "exclusivePriority": 1100,
      "coopPointIdList": [
        10340105
      ],
      "refreshNonCoopOnly": false
    }
  ],
  "eventId": 0,
  "associateActivity": 0
}