{
  "id" : 471,
  "taskType" : "WQ",
  "activeMode" : "PLAY_MODE_SINGLE",
  "luaPath" : "Actor/Quest/IQ471",
  "subQuests" : [ {
    "subId" : 47101,
    "mainId" : 471,
    "order" : 1,
    "showType" : "QUEST_HIDDEN",
    "acceptCondComb" : "LOGIC_AND",
    "acceptCond" : [ {
      "type" : "QUEST_COND_STATE_EQUAL",
      "param" : [ 46902, 3 ]
    }, {
      "type" : "QUEST_COND_STATE_NOT_EQUAL",
      "param" : [ 46904, 3 ]
    } ],
    "finishCond" : [ {
      "type" : "QUEST_CONTENT_FINISH_PLOT",
      "param" : [ 47101 ]
    } ],
    "finishParent" : true,
    "isRewind" : true
  }, {
    "subId" : 47102,
    "mainId" : 471,
    "order" : 2,
    "showType" : "QUEST_HIDDEN",
    "acceptCondComb" : "LOGIC_AND",
    "acceptCond" : [ {
      "type" : "QUEST_COND_STATE_EQUAL",
      "param" : [ 46902, 3 ]
    }, {
      "type" : "QUEST_COND_STATE_EQUAL",
      "param" : [ 46904, 3 ]
    } ],
    "finishCond" : [ {
      "type" : "QUEST_CONTENT_FINISH_PLOT",
      "param" : [ 47102 ]
    } ],
    "finishParent" : true,
    "isRewind" : true
  } ]
}