{
  "id" : 70519,
  "taskType" : "WQ",
  "luaPath" : "Actor/Quest/WQ70519",
  "rewardIdList" : [ 170519 ],
  "activityId" : 2016,
  "activityType" : "NEW_ACTIVITY_UNKNOWN_3103",
  "subQuests" : [ {
    "subId" : 7051901,
    "mainId" : 70519,
    "order" : 1,
    "showType" : "QUEST_HIDDEN",
    "acceptCondComb" : "LOGIC_AND",
    "acceptCond" : [ {
      "type" : "QUEST_COND_ACTIVITY_COND",
      "param" : [ 2016024, 1 ]
    }, {
      "type" : "QUEST_COND_STATE_EQUAL",
      "param" : [ 7051803, 3 ]
    } ],
    "finishCond" : [ {
      "type" : "QUEST_CONTENT_FINISH_PLOT",
      "param" : [ 7051901 ]
    } ],
    "isRewind" : true,
    "refreshNonCoopOnly" : true
  }, {
    "subId" : 7051902,
    "mainId" : 70519,
    "order" : 2,
    "acceptCond" : [ {
      "type" : "QUEST_COND_STATE_EQUAL",
      "param" : [ 7051901, 3 ]
    } ],
    "finishCond" : [ {
      "type" : "QUEST_CONTENT_COMPLETE_TALK",
      "param" : [ 7051902 ]
    } ],
    "guide" : {
      "type" : "QUEST_GUIDE_NPC",
      "autoGuide" : "QUEST_GUIDE_AUTO_ENABLE",
      "param" : [ "30234" ],
      "guideScene" : 3,
      "guideStyle" : "QUEST_GUIDE_STYLE_TARGET",
      "guideLayer" : "QUEST_GUIDE_LAYER_SCENE"
    },
    "finishParent" : true,
    "isRewind" : true,
    "finishExec" : [ {
      "type" : "QUEST_EXEC_REFRESH_GROUP_SUITE",
      "param" : [ "3", "133002149,2" ]
    } ],
    "beginExec" : [ {
      "type" : "QUEST_EXEC_REFRESH_GROUP_SUITE",
      "param" : [ "3", "133002149,1" ]
    } ],
    "exclusiveNpcList" : [ 30234 ],
    "exclusiveNpcPriority" : 1100
  }, {
    "subId" : 7051903,
    "mainId" : 70519,
    "order" : 3,
    "showType" : "QUEST_HIDDEN",
    "acceptCond" : [ {
      "type" : "QUEST_COND_STATE_EQUAL",
      "param" : [ 7051902, 2 ]
    } ],
    "finishCondComb" : "LOGIC_OR",
    "finishCond" : [ {
      "type" : "QUEST_CONTENT_FINISH_PLOT",
      "param" : [ 7051903 ]
    }, {
      "type" : "QUEST_CONTENT_QUEST_STATE_EQUAL",
      "param" : [ 7051902, 3 ]
    } ],
    "finishExec" : [ {
      "type" : "QUEST_EXEC_REFRESH_GROUP_SUITE",
      "param" : [ "3", "133002149,2" ]
    } ],
    "refreshNonCoopOnly" : true
  } ]
}