{
  "id": 71069,
  "collectionId": 0,
  "series": 0,
  "taskType": "WQ",
  "enabled": false,
  "luaPath": "Actor/Quest/WQ71069",
  "recommendLevel": 0,
  "repeatable": false,
  "chapterId": 0,
  "subQuests": [
    {
      "subId": 7106901,
      "mainId": 71069,
      "order": 1,
      "subQuestGroup": 0,
      "isMpBlock": false,
      "acceptCond": [
        {
          "type": "QUEST_COND_STATE_EQUAL",
          "param": [
            99902,
            3
          ],
          "count": 0
        }
      ],
      "finishCond": [
        {
          "type": "QUEST_CONTENT_QUEST_STATE_EQUAL",
          "param": [
            99902,
            3
          ],
          "count": 0
        }
      ],
      "showGuide": false,
      "finishParent": true,
      "failParent": false,
      "isRewind": true,
      "exclusivePriority": 0,
      "refreshNonCoopOnly": true
    }
  ],
  "eventId": 0,
  "associateActivity": 0
}