{
  "id": 72278,
  "collectionId": 4011,
  "series": 0,
  "taskType": "WQ",
  "enabled": true,
  "luaPath": "Actor/Quest/WQ72278",
  "recommendLevel": 0,
  "repeatable": false,
  "rewardIdList": [
    172278
  ],
  "chapterId": 0,
  "subQuests": [
    {
      "subId": 7227801,
      "mainId": 72278,
      "order": 2,
      "subQuestGroup": 0,
      "isMpBlock": false,
      "acceptCond": [
        {
          "type": "QUEST_COND_STATE_EQUAL",
          "param": [
            7227827,
            3
          ],
          "count": 0
        }
      ],
      "finishCond": [
        {
          "type": "QUEST_CONTENT_COMPLETE_TALK",
          "param": [
            7227801
          ],
          "count": 0
        }
      ],
      "guide": {
        "type": "QUEST_GUIDE_NPC",
        "param": [
          "1018"
        ],
        "guideScene": 3,
        "guideStyle": "QUEST_GUIDE_STYLE_START",
        "guideLayer": "QUEST_GUIDE_LAYER_SCENE"
      },
      "showGuide": false,
      "finishParent": false,
      "failParent": false,
      "isRewind": true,
      "exclusiveNpcList": [
        1018,
        10090
      ],
      "exclusivePriority": 1100,
      "exclusivePlaceList": [
        320905
      ],
      "refreshNonCoopOnly": true
    },
    {
      "subId": 7227802,
      "mainId": 72278,
      "order": 3,
      "subQuestGroup": 0,
      "isMpBlock": false,
      "acceptCond": [
        {
          "type": "QUEST_COND_STATE_EQUAL",
          "param": [
            7227801,
            3
          ],
          "count": 0
        }
      ],
      "finishCond": [
        {
          "type": "QUEST_CONTENT_FINISH_PLOT",
          "param": [
            7227802
          ],
          "count": 0
        }
      ],
      "guide": {
        "type": "QUEST_GUIDE_LOCATION",
        "param": [
          "Q7227803_N10000005",
          "0"
        ],
        "guideScene": 3,
        "guideStyle": "QUEST_GUIDE_STYLE_POINT",
        "guideLayer": "QUEST_GUIDE_LAYER_SCENE"
      },
      "showGuide": false,
      "finishParent": false,
      "failParent": false,
      "isRewind": true,
      "exclusiveNpcList": [
        1018,
        10090,
        12029
      ],
      "exclusivePriority": 1100,
      "exclusivePlaceList": [
        320905
      ],
      "refreshNonCoopOnly": true
    },
    {
      "subId": 7227803,
      "mainId": 72278,
      "order": 4,
      "subQuestGroup": 0,
      "isMpBlock": false,
      "acceptCond": [
        {
          "type": "QUEST_COND_STATE_EQUAL",
          "param": [
            7227802,
            3
          ],
          "count": 0
        }
      ],
      "finishCond": [
        {
          "type": "QUEST_CONTENT_COMPLETE_TALK",
          "param": [
            7227803
          ],
          "count": 0
        }
      ],
      "guide": {
        "type": "QUEST_GUIDE_NPC",
        "param": [
          "10090"
        ],
        "guideScene": 3,
        "guideStyle": "QUEST_GUIDE_STYLE_TARGET",
        "guideLayer": "QUEST_GUIDE_LAYER_SCENE"
      },
      "showGuide": false,
      "finishParent": false,
      "failParent": false,
      "isRewind": false,
      "exclusiveNpcList": [
        10090,
        12029
      ],
      "exclusivePriority": 1100,
      "exclusivePlaceList": [
        320905
      ],
      "refreshNonCoopOnly": true
    },
    {
      "subId": 7227804,
      "mainId": 72278,
      "order": 5,
      "subQuestGroup": 0,
      "isMpBlock": false,
      "acceptCond": [
        {
          "type": "QUEST_COND_STATE_EQUAL",
          "param": [
            7227803,
            3
          ],
          "count": 0
        }
      ],
      "finishCond": [
        {
          "type": "QUEST_CONTENT_FINISH_ITEM_GIVING",
          "param": [
            7227801
          ],
          "count": 0
        }
      ],
      "guide": {
        "type": "QUEST_GUIDE_NPC",
        "param": [
          "10090"
        ],
        "guideScene": 3,
        "guideStyle": "QUEST_GUIDE_STYLE_TARGET",
        "guideLayer": "QUEST_GUIDE_LAYER_SCENE"
      },
      "showGuide": false,
      "finishParent": false,
      "failParent": false,
      "isRewind": true,
      "beginExec": [
        {
          "type": "QUEST_EXEC_ACTIVE_ITEM_GIVING",
          "param": [
            "7227801"
          ]
        }
      ],
      "exclusiveNpcList": [
        10090,
        12029
      ],
      "exclusivePriority": 1100,
      "refreshNonCoopOnly": true
    },
    {
      "subId": 7227805,
      "mainId": 72278,
      "order": 6,
      "subQuestGroup": 0,
      "isMpBlock": false,
      "acceptCond": [
        {
          "type": "QUEST_COND_STATE_EQUAL",
          "param": [
            7227804,
            3
          ],
          "count": 0
        }
      ],
      "finishCond": [
        {
          "type": "QUEST_CONTENT_COMPLETE_TALK",
          "param": [
            7227805
          ],
          "count": 0
        }
      ],
      "guide": {
        "type": "QUEST_GUIDE_NPC",
        "param": [
          "10090"
        ],
        "guideScene": 3,
        "guideStyle": "QUEST_GUIDE_STYLE_TARGET",
        "guideLayer": "QUEST_GUIDE_LAYER_SCENE"
      },
      "showGuide": false,
      "finishParent": false,
      "failParent": false,
      "isRewind": true,
      "exclusiveNpcList": [
        10090,
        12029
      ],
      "exclusivePriority": 1100,
      "refreshNonCoopOnly": true
    },
    {
      "subId": 7227806,
      "mainId": 72278,
      "order": 7,
      "subQuestGroup": 0,
      "isMpBlock": false,
      "acceptCond": [
        {
          "type": "QUEST_COND_STATE_EQUAL",
          "param": [
            7227805,
            3
          ],
          "count": 0
        }
      ],
      "finishCond": [
        {
          "type": "QUEST_CONTENT_FINISH_PLOT",
          "param": [
            7227806
          ],
          "count": 0
        }
      ],
      "guide": {
        "type": "QUEST_GUIDE_LOCATION",
        "param": [
          "Q7227807_N10090",
          "15"
        ],
        "guideScene": 3,
        "guideStyle": "QUEST_GUIDE_STYLE_POINT",
        "guideLayer": "QUEST_GUIDE_LAYER_SCENE"
      },
      "showGuide": false,
      "finishParent": false,
      "failParent": false,
      "isRewind": true,
      "exclusiveNpcList": [
        10090,
        1035,
        12029,
        12028,
        12027,
        3035
      ],
      "exclusivePriority": 1100,
      "refreshNonCoopOnly": true
    },
    {
      "subId": 7227807,
      "mainId": 72278,
      "order": 8,
      "subQuestGroup": 0,
      "isMpBlock": false,
      "acceptCond": [
        {
          "type": "QUEST_COND_STATE_EQUAL",
          "param": [
            7227806,
            3
          ],
          "count": 0
        }
      ],
      "finishCond": [
        {
          "type": "QUEST_CONTENT_COMPLETE_TALK",
          "param": [
            7227807
          ],
          "count": 0
        }
      ],
      "guide": {
        "type": "QUEST_GUIDE_NPC",
        "param": [
          "1035"
        ],
        "guideScene": 3,
        "guideStyle": "QUEST_GUIDE_STYLE_TARGET",
        "guideLayer": "QUEST_GUIDE_LAYER_SCENE"
      },
      "showGuide": false,
      "finishParent": false,
      "failParent": false,
      "isRewind": false,
      "exclusiveNpcList": [
        10090,
        1035,
        12029,
        12028,
        12027,
        3035
      ],
      "exclusivePriority": 1100,
      "refreshNonCoopOnly": true
    },
    {
      "subId": 7227808,
      "mainId": 72278,
      "order": 9,
      "subQuestGroup": 0,
      "isMpBlock": false,
      "acceptCond": [
        {
          "type": "QUEST_COND_STATE_EQUAL",
          "param": [
            7227807,
            3
          ],
          "count": 0
        }
      ],
      "finishCond": [
        {
          "type": "QUEST_CONTENT_FINISH_PLOT",
          "param": [
            7227808
          ],
          "count": 0
        }
      ],
      "guide": {
        "type": "QUEST_GUIDE_LOCATION",
        "param": [
          "guide_Q7227808",
          "0"
        ],
        "guideScene": 3,
        "guideStyle": "QUEST_GUIDE_STYLE_POINT",
        "guideLayer": "QUEST_GUIDE_LAYER_SCENE"
      },
      "showGuide": false,
      "finishParent": false,
      "failParent": false,
      "isRewind": true,
      "exclusiveNpcList": [
        10090,
        1035,
        12029,
        12028,
        12027,
        3035,
        30065
      ],
      "exclusivePriority": 1100,
      "exclusivePlaceList": [
        72278
      ],
      "refreshNonCoopOnly": true
    },
    {
      "subId": 7227809,
      "mainId": 72278,
      "order": 11,
      "subQuestGroup": 0,
      "isMpBlock": false,
      "acceptCond": [
        {
          "type": "QUEST_COND_STATE_EQUAL",
          "param": [
            7227826,
            3
          ],
          "count": 0
        }
      ],
      "finishCond": [
        {
          "type": "QUEST_CONTENT_COMPLETE_TALK",
          "param": [
            7227809
          ],
          "count": 0
        }
      ],
      "guide": {
        "type": "QUEST_GUIDE_NPC",
        "param": [
          "10090"
        ],
        "guideScene": 3,
        "guideStyle": "QUEST_GUIDE_STYLE_TARGET",
        "guideLayer": "QUEST_GUIDE_LAYER_SCENE"
      },
      "showGuide": false,
      "finishParent": false,
      "failParent": false,
      "isRewind": false,
      "exclusiveNpcList": [
        10090,
        1035,
        30065
      ],
      "exclusivePriority": 1100,
      "exclusivePlaceList": [
        72278
      ],
      "refreshNonCoopOnly": true
    },
    {
      "subId": 7227810,
      "mainId": 72278,
      "order": 12,
      "subQuestGroup": 0,
      "isMpBlock": false,
      "acceptCond": [
        {
          "type": "QUEST_COND_STATE_EQUAL",
          "param": [
            7227809,
            3
          ],
          "count": 0
        }
      ],
      "finishCond": [
        {
          "type": "QUEST_CONTENT_FINISH_PLOT",
          "param": [
            7227810
          ],
          "count": 0
        }
      ],
      "guide": {
        "type": "QUEST_GUIDE_NPC",
        "param": [
          "10090"
        ],
        "guideScene": 3,
        "guideStyle": "QUEST_GUIDE_STYLE_TARGET",
        "guideLayer": "QUEST_GUIDE_LAYER_SCENE"
      },
      "showGuide": true,
      "finishParent": false,
      "failParent": false,
      "isRewind": true,
      "exclusiveNpcList": [
        10090,
        1035
      ],
      "exclusivePriority": 1100,
      "exclusivePlaceList": [
        72278
      ],
      "refreshNonCoopOnly": true
    },
    {
      "subId": 7227811,
      "mainId": 72278,
      "order": 13,
      "subQuestGroup": 0,
      "isMpBlock": false,
      "acceptCond": [
        {
          "type": "QUEST_COND_STATE_EQUAL",
          "param": [
            99902,
            3
          ],
          "count": 0
        }
      ],
      "finishCond": [
        {
          "type": "QUEST_CONTENT_FINISH_PLOT",
          "param": [
            7227811
          ],
          "count": 0
        }
      ],
      "guide": {
        "type": "QUEST_GUIDE_LOCATION",
        "param": [
          "guide_Q7227811"
        ],
        "guideScene": 3,
        "guideStyle": "QUEST_GUIDE_STYLE_POINT",
        "guideLayer": "QUEST_GUIDE_LAYER_SCENE"
      },
      "showGuide": true,
      "finishParent": false,
      "failParent": false,
      "isRewind": false,
      "exclusiveNpcList": [
        10090,
        1035
      ],
      "exclusivePriority": 1100,
      "exclusivePlaceList": [
        72278
      ],
      "refreshNonCoopOnly": true
    },
    {
      "subId": 7227812,
      "mainId": 72278,
      "order": 14,
      "subQuestGroup": 0,
      "isMpBlock": false,
      "acceptCond": [
        {
          "type": "QUEST_COND_STATE_EQUAL",
          "param": [
            99902,
            3
          ],
          "count": 0
        }
      ],
      "finishCond": [
        {
          "type": "QUEST_CONTENT_FINISH_PLOT",
          "param": [
            7227812
          ],
          "count": 0
        }
      ],
      "guide": {
        "type": "QUEST_GUIDE_NPC",
        "param": [
          "10090"
        ],
        "guideScene": 3,
        "guideStyle": "QUEST_GUIDE_STYLE_TARGET",
        "guideLayer": "QUEST_GUIDE_LAYER_SCENE"
      },
      "showGuide": true,
      "finishParent": false,
      "failParent": false,
      "isRewind": false,
      "exclusiveNpcList": [
        10090,
        1035
      ],
      "exclusivePriority": 1100,
      "exclusivePlaceList": [
        72278
      ],
      "refreshNonCoopOnly": true
    },
    {
      "subId": 7227813,
      "mainId": 72278,
      "order": 15,
      "subQuestGroup": 0,
      "isMpBlock": false,
      "acceptCond": [
        {
          "type": "QUEST_COND_STATE_EQUAL",
          "param": [
            99902,
            3
          ],
          "count": 0
        }
      ],
      "finishCond": [
        {
          "type": "QUEST_CONTENT_FINISH_PLOT",
          "param": [
            7227813
          ],
          "count": 0
        }
      ],
      "guide": {
        "type": "QUEST_GUIDE_LOCATION",
        "param": [
          "guide_Q7227813"
        ],
        "guideScene": 3,
        "guideStyle": "QUEST_GUIDE_STYLE_POINT",
        "guideLayer": "QUEST_GUIDE_LAYER_SCENE"
      },
      "showGuide": true,
      "finishParent": false,
      "failParent": false,
      "isRewind": false,
      "exclusiveNpcList": [
        10090,
        1035
      ],
      "exclusivePriority": 1100,
      "exclusivePlaceList": [
        72278
      ],
      "refreshNonCoopOnly": true
    },
    {
      "subId": 7227814,
      "mainId": 72278,
      "order": 16,
      "subQuestGroup": 0,
      "isMpBlock": false,
      "acceptCond": [
        {
          "type": "QUEST_COND_STATE_EQUAL",
          "param": [
            99902,
            3
          ],
          "count": 0
        }
      ],
      "finishCond": [
        {
          "type": "QUEST_CONTENT_FINISH_PLOT",
          "param": [
            7227814
          ],
          "count": 0
        }
      ],
      "guide": {
        "type": "QUEST_GUIDE_NPC",
        "param": [
          "10090"
        ],
        "guideScene": 3,
        "guideStyle": "QUEST_GUIDE_STYLE_TARGET",
        "guideLayer": "QUEST_GUIDE_LAYER_SCENE"
      },
      "showGuide": true,
      "finishParent": false,
      "failParent": false,
      "isRewind": false,
      "exclusiveNpcList": [
        10090,
        1035
      ],
      "exclusivePriority": 1100,
      "exclusivePlaceList": [
        72278
      ],
      "refreshNonCoopOnly": true
    },
    {
      "subId": 7227815,
      "mainId": 72278,
      "order": 17,
      "subQuestGroup": 0,
      "isMpBlock": false,
      "acceptCond": [
        {
          "type": "QUEST_COND_STATE_EQUAL",
          "param": [
            99902,
            3
          ],
          "count": 0
        }
      ],
      "finishCond": [
        {
          "type": "QUEST_CONTENT_FINISH_PLOT",
          "param": [
            7227815
          ],
          "count": 0
        }
      ],
      "guide": {
        "type": "QUEST_GUIDE_LOCATION",
        "param": [
          "guide_Q7227815"
        ],
        "guideScene": 3,
        "guideStyle": "QUEST_GUIDE_STYLE_POINT",
        "guideLayer": "QUEST_GUIDE_LAYER_SCENE"
      },
      "showGuide": true,
      "finishParent": false,
      "failParent": false,
      "isRewind": false,
      "exclusiveNpcList": [
        10090,
        1035
      ],
      "exclusivePriority": 1100,
      "exclusivePlaceList": [
        72278
      ],
      "refreshNonCoopOnly": true
    },
    {
      "subId": 7227816,
      "mainId": 72278,
      "order": 18,
      "subQuestGroup": 0,
      "isMpBlock": false,
      "acceptCond": [
        {
          "type": "QUEST_COND_STATE_EQUAL",
          "param": [
            7227810,
            3
          ],
          "count": 0
        }
      ],
      "finishCond": [
        {
          "type": "QUEST_CONTENT_COMPLETE_TALK",
          "param": [
            7227816
          ],
          "count": 0
        }
      ],
      "guide": {
        "type": "QUEST_GUIDE_LOCATION",
        "param": [
          "guide_Q7227815",
          "10"
        ],
        "guideScene": 3,
        "guideStyle": "QUEST_GUIDE_STYLE_POINT",
        "guideLayer": "QUEST_GUIDE_LAYER_SCENE"
      },
      "showGuide": false,
      "finishParent": false,
      "failParent": false,
      "isRewind": true,
      "exclusiveNpcList": [
        10090,
        1035
      ],
      "exclusivePriority": 1100,
      "exclusivePlaceList": [
        72278
      ],
      "refreshNonCoopOnly": true
    },
    {
      "subId": 7227817,
      "mainId": 72278,
      "order": 19,
      "subQuestGroup": 0,
      "isMpBlock": false,
      "acceptCond": [
        {
          "type": "QUEST_COND_STATE_EQUAL",
          "param": [
            7227816,
            3
          ],
          "count": 0
        }
      ],
      "finishCond": [
        {
          "type": "QUEST_CONTENT_FINISH_PLOT",
          "param": [
            7227817
          ],
          "count": 0
        }
      ],
      "guide": {
        "type": "QUEST_GUIDE_LOCATION",
        "param": [
          "Q7227807_N10090",
          "15"
        ],
        "guideScene": 3,
        "guideStyle": "QUEST_GUIDE_STYLE_POINT",
        "guideLayer": "QUEST_GUIDE_LAYER_SCENE"
      },
      "showGuide": false,
      "finishParent": false,
      "failParent": false,
      "isRewind": true,
      "exclusiveNpcList": [
        10090,
        1035,
        3035
      ],
      "exclusivePriority": 1100,
      "refreshNonCoopOnly": true
    },
    {
      "subId": 7227818,
      "mainId": 72278,
      "order": 20,
      "subQuestGroup": 0,
      "isMpBlock": false,
      "acceptCond": [
        {
          "type": "QUEST_COND_STATE_EQUAL",
          "param": [
            7227817,
            3
          ],
          "count": 0
        }
      ],
      "finishCond": [
        {
          "type": "QUEST_CONTENT_COMPLETE_TALK",
          "param": [
            7227818
          ],
          "count": 0
        }
      ],
      "guide": {
        "type": "QUEST_GUIDE_NPC",
        "param": [
          "10090"
        ],
        "guideScene": 3,
        "guideStyle": "QUEST_GUIDE_STYLE_TARGET",
        "guideLayer": "QUEST_GUIDE_LAYER_SCENE"
      },
      "showGuide": false,
      "finishParent": false,
      "failParent": false,
      "isRewind": false,
      "exclusiveNpcList": [
        10090,
        1035,
        3035
      ],
      "exclusivePriority": 1100,
      "refreshNonCoopOnly": true
    },
    {
      "subId": 7227819,
      "mainId": 72278,
      "order": 21,
      "subQuestGroup": 0,
      "isMpBlock": false,
      "acceptCond": [
        {
          "type": "QUEST_COND_STATE_EQUAL",
          "param": [
            7227818,
            3
          ],
          "count": 0
        }
      ],
      "finishCond": [
        {
          "type": "QUEST_CONTENT_LUA_NOTIFY",
          "paramStr": "1332207371",
          "count": 1
        }
      ],
      "guide": {
        "type": "QUEST_GUIDE_LOCATION",
        "param": [
          "Q7227819"
        ],
        "guideScene": 3,
        "guideStyle": "QUEST_GUIDE_STYLE_POINT",
        "guideLayer": "QUEST_GUIDE_LAYER_SCENE"
      },
      "showGuide": false,
      "finishParent": false,
      "failParent": false,
      "isRewind": true,
      "finishExec": [
        {
          "type": "QUEST_EXEC_UNREGISTER_DYNAMIC_GROUP",
          "param": [
            "133220737",
            "0"
          ]
        }
      ],
      "beginExec": [
        {
          "type": "QUEST_EXEC_REGISTER_DYNAMIC_GROUP",
          "param": [
            "3",
            "133220737"
          ]
        }
      ],
      "exclusiveNpcList": [
        10090,
        1035,
        3035
      ],
      "exclusivePriority": 1100,
      "refreshNonCoopOnly": true
    },
    {
      "subId": 7227820,
      "mainId": 72278,
      "order": 22,
      "subQuestGroup": 0,
      "isMpBlock": false,
      "acceptCond": [
        {
          "type": "QUEST_COND_STATE_EQUAL",
          "param": [
            7227819,
            3
          ],
          "count": 0
        }
      ],
      "finishCond": [
        {
          "type": "QUEST_CONTENT_COMPLETE_TALK",
          "param": [
            7227820
          ],
          "count": 0
        }
      ],
      "guide": {
        "type": "QUEST_GUIDE_LOCATION",
        "param": [
          "Q7227819"
        ],
        "guideScene": 3,
        "guideStyle": "QUEST_GUIDE_STYLE_POINT",
        "guideLayer": "QUEST_GUIDE_LAYER_SCENE"
      },
      "showGuide": false,
      "finishParent": false,
      "failParent": false,
      "isRewind": false,
      "exclusiveNpcList": [
        10090,
        1035,
        3035
      ],
      "exclusivePriority": 1100,
      "refreshNonCoopOnly": true
    },
    {
      "subId": 7227821,
      "mainId": 72278,
      "order": 23,
      "subQuestGroup": 0,
      "isMpBlock": false,
      "acceptCond": [
        {
          "type": "QUEST_COND_STATE_EQUAL",
          "param": [
            7227820,
            3
          ],
          "count": 0
        }
      ],
      "finishCond": [
        {
          "type": "QUEST_CONTENT_COMPLETE_TALK",
          "param": [
            7227822
          ],
          "count": 0
        }
      ],
      "guide": {
        "type": "QUEST_GUIDE_LOCATION",
        "param": [
          "guide_Q7227821",
          "0"
        ],
        "guideScene": 3,
        "guideStyle": "QUEST_GUIDE_STYLE_POINT",
        "guideLayer": "QUEST_GUIDE_LAYER_SCENE"
      },
      "showGuide": false,
      "finishParent": false,
      "failParent": false,
      "isRewind": true,
      "exclusiveNpcList": [
        1018,
        10090,
        1035,
        1034,
        3030,
        3035
      ],
      "exclusivePriority": 1100,
      "exclusivePlaceList": [
        4005402
      ],
      "refreshNonCoopOnly": true
    },
    {
      "subId": 7227822,
      "mainId": 72278,
      "order": 24,
      "subQuestGroup": 0,
      "isMpBlock": false,
      "acceptCond": [
        {
          "type": "QUEST_COND_STATE_EQUAL",
          "param": [
            99902,
            3
          ],
          "count": 0
        }
      ],
      "finishCond": [
        {
          "type": "QUEST_CONTENT_COMPLETE_TALK",
          "param": [
            7227822
          ],
          "count": 0
        }
      ],
      "guide": {
        "type": "QUEST_GUIDE_NPC",
        "param": [
          "10090"
        ],
        "guideScene": 3,
        "guideStyle": "QUEST_GUIDE_STYLE_TARGET",
        "guideLayer": "QUEST_GUIDE_LAYER_SCENE"
      },
      "showGuide": false,
      "finishParent": false,
      "failParent": false,
      "isRewind": false,
      "exclusivePriority": 0,
      "exclusivePlaceList": [
        4005402
      ],
      "refreshNonCoopOnly": true
    },
    {
      "subId": 7227823,
      "mainId": 72278,
      "order": 25,
      "subQuestGroup": 0,
      "isMpBlock": false,
      "acceptCond": [
        {
          "type": "QUEST_COND_STATE_EQUAL",
          "param": [
            7227821,
            3
          ],
          "count": 0
        }
      ],
      "finishCond": [
        {
          "type": "QUEST_CONTENT_GAME_TIME_TICK",
          "param": [
            1
          ],
          "paramStr": "14,16",
          "count": 0
        }
      ],
      "showGuide": true,
      "finishParent": false,
      "failParent": false,
      "isRewind": true,
      "exclusiveNpcList": [
        10090,
        1035,
        3030
      ],
      "exclusivePriority": 1100,
      "exclusivePlaceList": [
        72279
      ],
      "refreshNonCoopOnly": true
    },
    {
      "subId": 7227824,
      "mainId": 72278,
      "order": 26,
      "subQuestGroup": 0,
      "isMpBlock": false,
      "acceptCond": [
        {
          "type": "QUEST_COND_STATE_EQUAL",
          "param": [
            7227823,
            3
          ],
          "count": 0
        }
      ],
      "finishCond": [
        {
          "type": "QUEST_CONTENT_FINISH_PLOT",
          "param": [
            7227824
          ],
          "count": 0
        }
      ],
      "guide": {
        "type": "QUEST_GUIDE_LOCATION",
        "param": [
          "Q7227825_N10000005",
          "10"
        ],
        "guideScene": 3,
        "guideStyle": "QUEST_GUIDE_STYLE_POINT",
        "guideLayer": "QUEST_GUIDE_LAYER_SCENE"
      },
      "showGuide": false,
      "finishParent": false,
      "failParent": false,
      "isRewind": true,
      "exclusiveNpcList": [
        10090,
        1035,
        3030
      ],
      "exclusivePriority": 1100,
      "exclusivePlaceList": [
        72279
      ],
      "refreshNonCoopOnly": true
    },
    {
      "subId": 7227825,
      "mainId": 72278,
      "order": 27,
      "subQuestGroup": 0,
      "isMpBlock": false,
      "acceptCond": [
        {
          "type": "QUEST_COND_STATE_EQUAL",
          "param": [
            7227824,
            3
          ],
          "count": 0
        }
      ],
      "finishCondComb": "LOGIC_OR",
      "finishCond": [
        {
          "type": "QUEST_CONTENT_COMPLETE_TALK",
          "param": [
            7227824
          ],
          "count": 0
        },
        {
          "type": "QUEST_CONTENT_COMPLETE_TALK",
          "param": [
            7227828
          ],
          "count": 0
        }
      ],
      "guide": {
        "type": "QUEST_GUIDE_NPC",
        "param": [
          "10090"
        ],
        "guideScene": 3,
        "guideStyle": "QUEST_GUIDE_STYLE_TARGET",
        "guideLayer": "QUEST_GUIDE_LAYER_SCENE"
      },
      "showGuide": false,
      "finishParent": false,
      "failParent": false,
      "isRewind": false,
      "exclusiveNpcList": [
        10090,
        1035,
        3030
      ],
      "exclusivePriority": 1100,
      "exclusivePlaceList": [
        72279
      ],
      "refreshNonCoopOnly": true
    },
    {
      "subId": 7227826,
      "mainId": 72278,
      "order": 10,
      "subQuestGroup": 0,
      "isMpBlock": false,
      "acceptCond": [
        {
          "type": "QUEST_COND_STATE_EQUAL",
          "param": [
            7227808,
            3
          ],
          "count": 0
        }
      ],
      "finishCond": [
        {
          "type": "QUEST_CONTENT_FINISH_PLOT",
          "param": [
            7227826
          ],
          "count": 0
        }
      ],
      "guide": {
        "type": "QUEST_GUIDE_LOCATION",
        "param": [
          "guide_Q7227808",
          "0"
        ],
        "guideScene": 3,
        "guideStyle": "QUEST_GUIDE_STYLE_POINT",
        "guideLayer": "QUEST_GUIDE_LAYER_SCENE"
      },
      "showGuide": false,
      "finishParent": false,
      "failParent": false,
      "isRewind": true,
      "exclusiveNpcList": [
        10090,
        1035,
        30065
      ],
      "exclusivePriority": 1100,
      "exclusivePlaceList": [
        72278
      ],
      "refreshNonCoopOnly": true
    },
    {
      "subId": 7227827,
      "mainId": 72278,
      "order": 1,
      "subQuestGroup": 0,
      "isMpBlock": false,
      "showType": "QUEST_HIDDEN",
      "acceptCondComb": "LOGIC_AND",
      "acceptCond": [
        {
          "type": "QUEST_COND_ACTIVITY_COND",
          "param": [
            2012021,
            1
          ],
          "count": 0
        },
        {
          "type": "QUEST_COND_STATE_EQUAL",
          "param": [
            4005513,
            3
          ],
          "count": 0
        }
      ],
      "finishCond": [
        {
          "type": "QUEST_CONTENT_FINISH_PLOT",
          "param": [
            7227827
          ],
          "count": 0
        }
      ],
      "showGuide": true,
      "finishParent": false,
      "failParent": false,
      "isRewind": true,
      "exclusivePriority": 0,
      "refreshNonCoopOnly": true
    },
    {
      "subId": 7227828,
      "mainId": 72278,
      "order": 28,
      "subQuestGroup": 0,
      "isMpBlock": false,
      "showType": "QUEST_HIDDEN",
      "acceptCond": [
        {
          "type": "QUEST_COND_COMPLETE_TALK",
          "param": [
            7227828
          ],
          "count": 0
        }
      ],
      "finishCond": [
        {
          "type": "QUEST_CONTENT_GAME_TIME_TICK",
          "paramStr": "0,24",
          "count": 0
        }
      ],
      "showGuide": false,
      "finishParent": true,
      "failParent": false,
      "isRewind": false,
      "gainItems": [
        {
          "id": 101797,
          "count": 1
        }
      ],
      "finishExec": [
        {
          "type": "QUEST_EXEC_SET_QUEST_GLOBAL_VAR",
          "param": [
            "7227801",
            "1"
          ]
        }
      ],
      "exclusivePriority": 0,
      "refreshNonCoopOnly": true
    },
    {
      "subId": 7227829,
      "mainId": 72278,
      "order": 29,
      "subQuestGroup": 0,
      "isMpBlock": false,
      "showType": "QUEST_HIDDEN",
      "acceptCond": [
        {
          "type": "QUEST_COND_COMPLETE_TALK",
          "param": [
            7227824
          ],
          "count": 0
        }
      ],
      "finishCond": [
        {
          "type": "QUEST_CONTENT_GAME_TIME_TICK",
          "paramStr": "0,24",
          "count": 0
        }
      ],
      "showGuide": false,
      "finishParent": true,
      "failParent": false,
      "isRewind": false,
      "gainItems": [
        {
          "id": 101769,
          "count": 1
        }
      ],
      "finishExec": [
        {
          "type": "QUEST_EXEC_SET_QUEST_GLOBAL_VAR",
          "param": [
            "7227801",
            "1"
          ]
        }
      ],
      "exclusivePriority": 0,
      "refreshNonCoopOnly": true
    }
  ],
  "eventId": 0,
  "associateActivity": 2012,
  "activityType": "NEW_ACTIVITY_IRODORI"
}